MANIFEST.in
README.md
setup.py
pyqt5Custom/__init__.py
pyqt5Custom/animation.py
pyqt5Custom/codetextedit.py
pyqt5Custom/colorpicker.py
pyqt5Custom/dragdropfile.py
pyqt5Custom/embedwindow.py
pyqt5Custom/imagebox.py
pyqt5Custom/requesthandler.py
pyqt5Custom/segbtngroup.py
pyqt5Custom/spinner.py
pyqt5Custom/styledbutton.py
pyqt5Custom/syntaxhighlighter.py
pyqt5Custom/titlebar.py
pyqt5Custom/toast.py
pyqt5Custom/toggleswitch.py
pyqt5Custom.egg-info/PKG-INFO
pyqt5Custom.egg-info/SOURCES.txt
pyqt5Custom.egg-info/dependency_links.txt
pyqt5Custom.egg-info/requires.txt
pyqt5Custom.egg-info/top_level.txt
pyqt5Custom/syntax/cpp.json
pyqt5Custom/syntax/python.json
pyqt5Custom/themes/default.json
pyqt5Custom/themes/monokai.json
pyqt5Custom/themes/oceanic.json
pyqt5Custom/themes/one-dark.json
pyqt5Custom/themes/one-light.json
pyqt5Custom/themes/zenburn.json